huum/__init__.py
huum/const.py
huum/exceptions.py
huum/huum.py
huum/schemas.py
huum-0.8.1.dist-info/LICENSE
huum-0.8.1.dist-info/METADATA
huum-0.8.1.dist-info/WHEEL
huum-0.8.1.dist-info/RECORD
