Metadata-Version: 2.3
Name: huum
Version: 0.8.1
Summary: Python library for Huum saunas
License: MIT
Author: Frank Wickström
Author-email: frwickst@gmail.com
Requires-Python: >3.9
Classifier: License :: OSI Approved :: MIT License
Classifier: Programming Language :: Python :: 3
Classifier: Programming Language :: Python :: 3.10
Classifier: Programming Language :: Python :: 3.11
Classifier: Programming Language :: Python :: 3.12
Classifier: Programming Language :: Python :: 3.13
Provides-Extra: aiohttp
Requires-Dist: aiohttp[speedups] (>=3.12.12,<4.0.0) ; extra == "aiohttp"
Requires-Dist: mashumaro (>=3.16,<4.0)
Project-URL: Repository, https://github.com/frwickst/pyhuum
